INSTALL
LICENSE
MANIFEST.in
README
setup.py
bin/poachplate
poachplate.egg-info/PKG-INFO
poachplate.egg-info/SOURCES.txt
poachplate.egg-info/dependency_links.txt
poachplate.egg-info/top_level.txt
poachplatelib/__init__.py
poachplatelib/meta.py
poachplatelib/package.py
test/testpoachplate.py