Metadata-Version: 1.0
Name: poachplate
Version: 0.1.3
Summary: a script to create python script boilerplate (setup.py/package/README/etc)
Home-page: UNKNOWN
Author: matt harrison
Author-email: UNKNOWN
License: UNKNOWN
Platform: UNKNOWN
